dice_calc/__init__.py
dice_calc/altcast.py
dice_calc/blackrv.py
dice_calc/decorators.py
dice_calc/factory.py
dice_calc/funclib.py
dice_calc/output.py
dice_calc/randvar.py
dice_calc/roller.py
dice_calc/seq.py
dice_calc/settings.py
dice_calc/string_rvs.py
dice_calc/typings.py
dice_calc/utils.py
dice_calc/parser/__init__.py
dice_calc/parser/example_parse.py
dice_calc/parser/myparser.py
dice_calc/parser/parse_and_exec.py
dice_calc/parser/python_resolver.py
dice_calc/parser/ply/__init__.py
dice_calc/parser/ply/lex.py
dice_calc/parser/ply/yacc.py
dice_calc-0.3.6.dist-info/LICENSE
dice_calc-0.3.6.dist-info/METADATA
dice_calc-0.3.6.dist-info/WHEEL
dice_calc-0.3.6.dist-info/top_level.txt
dice_calc-0.3.6.dist-info/RECORD
