Metadata-Version: 2.2
Name: dice_calc
Version: 0.3.6
Summary: Advanced Calculator for Dice
Author: Ar-Kareem
Maintainer: Ar-Kareem
License: MIT License
Project-URL: Homepage, https://github.com/Ar-Kareem/PythonDice/
Project-URL: Repository, https://github.com/Ar-Kareem/PythonDice/
Project-URL: Issues, https://github.com/Ar-Kareem/PythonDice/issues
Keywords: dice,calculator,probability,statistics,math,dice-notation,dice-roller,dice-roller-simulator,dice-notation-parser,dice-notation-compiler,dice-notation-interpreter,dice-notation-evaluator,dice-notation-calculator,dice-notation-solver,dice-notation-simulator,dice-notation-optimizer,anydice,anydice-compiler,anydice-interpreter,anydice-evaluator,anydice-calculator,anydice-solver,anydice-simulator,python-dice
Classifier: Development Status :: 4 - Beta
Classifier: Intended Audience :: Developers
Classifier: Intended Audience :: Education
Classifier: Intended Audience :: Science/Research
Classifier: License :: OSI Approved :: MIT License
Classifier: Programming Language :: Python :: 3.9
Classifier: Programming Language :: Python :: 3.10
Classifier: Programming Language :: Python :: 3.11
Classifier: Programming Language :: Python :: 3.12
Requires-Python: >=3.9.0
License-File: LICENSE
